plone.app.imagecropping-3.0.2-py3.11-nspkg.pth
plone/app/imagecropping/__init__.py
plone/app/imagecropping/behaviors.py
plone/app/imagecropping/configure.zcml
plone/app/imagecropping/dx.py
plone/app/imagecropping/events.py
plone/app/imagecropping/interfaces.py
plone/app/imagecropping/setuphandlers.py
plone/app/imagecropping/storage.py
plone/app/imagecropping/subscribers.py
plone/app/imagecropping/testing.py
plone/app/imagecropping/testing.zcml
plone/app/imagecropping/browser/__init__.py
plone/app/imagecropping/browser/configure.zcml
plone/app/imagecropping/browser/crop.py
plone/app/imagecropping/browser/editor.pt
plone/app/imagecropping/browser/editor.py
plone/app/imagecropping/browser/settings.py
plone/app/imagecropping/browser/static/cropscaleselect.css
plone/app/imagecropping/browser/static/cropscaleselect.css.map
plone/app/imagecropping/browser/static/cropscaleselect.min.css
plone/app/imagecropping/browser/static/cropscaleselect.min.css.map
plone/app/imagecropping/browser/static/imagecropping-remote.min.js
plone/app/imagecropping/browser/static/imagecropping-remote.min.js.map
plone/app/imagecropping/browser/static/imagecropping.min.js
plone/app/imagecropping/browser/static/imagecropping.min.js.map
plone/app/imagecropping/browser/static/chunks/112.cde2554e94a994f47818.min.js
plone/app/imagecropping/browser/static/chunks/112.cde2554e94a994f47818.min.js.map
plone/app/imagecropping/browser/static/chunks/129.118805139385c0137e27.min.js
plone/app/imagecropping/browser/static/chunks/129.118805139385c0137e27.min.js.map
plone/app/imagecropping/browser/static/chunks/191.748d74d647a027a40c6b.min.js
plone/app/imagecropping/browser/static/chunks/191.748d74d647a027a40c6b.min.js.map
plone/app/imagecropping/browser/static/chunks/41.48210d2299ecbde0e7e3.min.js
plone/app/imagecropping/browser/static/chunks/41.48210d2299ecbde0e7e3.min.js.map
plone/app/imagecropping/browser/static/chunks/755.c2e3d18449410559633e.min.js
plone.app.imagecropping-3.0.2.dist-info/METADATA
plone.app.imagecropping-3.0.2.dist-info/WHEEL
plone.app.imagecropping-3.0.2.dist-info/entry_points.txt
plone.app.imagecropping-3.0.2.dist-info/namespace_packages.txt
plone.app.imagecropping-3.0.2.dist-info/top_level.txt
plone.app.imagecropping-3.0.2.dist-info/RECORD
