Metadata-Version: 2.1
Name: plone.app.imagecropping
Version: 3.0.2
Summary: Crops Images in Plone manually using cropper JS library
Home-page: https://github.com/collective/plone.app.imagecropping
Author: Plone Collective
Author-email: plone-developers@lists.sourceforge.net
License: GPLv2
Keywords: plone image crop
Classifier: Development Status :: 5 - Production/Stable
Classifier: Environment :: Web Environment
Classifier: Framework :: Plone
Classifier: Framework :: Plone :: Addon
Classifier: Framework :: Plone :: 6.0
Classifier: License :: OSI Approved :: GNU General Public License v2 (GPLv2)
Classifier: Operating System :: OS Independent
Classifier: Programming Language :: JavaScript
Classifier: Programming Language :: Python
Classifier: Programming Language :: Python :: 3.8
Classifier: Programming Language :: Python :: 3.9
Classifier: Programming Language :: Python :: 3.10
Classifier: Topic :: Software Development :: Libraries :: Python Modules
Requires-Python: >=3.8
Requires-Dist: Pillow
Requires-Dist: plone.app.dexterity
Requires-Dist: plone.app.registry
Requires-Dist: plone.base
Requires-Dist: plone.behavior
Requires-Dist: plone.dexterity
Requires-Dist: plone.namedfile (>=6.0.0)
Requires-Dist: plone.registry
Requires-Dist: plone.scale
Requires-Dist: plone.z3cform
Requires-Dist: Products.CMFCore
Requires-Dist: Products.GenericSetup
Requires-Dist: setuptools
Requires-Dist: z3c.caching
Requires-Dist: z3c.form
Provides-Extra: test
Requires-Dist: plone.api ; extra == 'test'
Requires-Dist: plone.app.contenttypes ; extra == 'test'
Requires-Dist: plone.app.testing ; extra == 'test'
Requires-Dist: plone.app.robotframework[debug] ; extra == 'test'
Requires-Dist: plone.browserlayer ; extra == 'test'
Requires-Dist: plone.testing ; extra == 'test'
Requires-Dist: robotsuite ; extra == 'test'
